c3p/__init__.py
c3p/agentic/__init__.py
c3p/agentic/c3p_agent.py
c3p/analyze_differences.py
c3p/benchmark_validator.py
c3p/chebi_classifier.py
c3p/classifier.py
c3p/cli.py
c3p/clients/__init__.py
c3p/clients/chebifier.py
c3p/combine_cli.py
c3p/compare_cli.py
c3p/curated/__init__.py
c3p/curated/triglyceride.py
c3p/datamodel.py
c3p/dumper.py
c3p/enrichment.py
c3p/extractor.py
c3p/learn.py
c3p/learn_cli.py
c3p/maftools.py
c3p/outcome_stats.py
c3p/plotting.py
c3p/programs/11_12_saturated_fatty_acyl_CoA_4__.py
c3p/programs/11_oxo_steroid.py
c3p/programs/11beta_hydroxy_steroid.py
c3p/programs/16beta_hydroxy_steroid.py
c3p/programs/17alpha_hydroxy_steroid.py
c3p/programs/17beta_hydroxy_steroid.py
c3p/programs/1_2_4_triazines.py
c3p/programs/1_2_diacyl_sn_glycero_3_phosphocholine.py
c3p/programs/1_O_acylglycerophosphoethanolamine.py
c3p/programs/1_acyl_sn_glycero_3_phosphoethanolamine.py
c3p/programs/1_acyl_sn_glycero_3_phosphoserine.py
c3p/programs/1_monoglyceride.py
c3p/programs/1_phosphatidyl_1D_myo_inositol.py
c3p/programs/2_5_diketopiperazines.py
c3p/programs/2__deoxyribonucleoside_5__monophosphate.py
c3p/programs/2_acyl_1_alkyl_sn_glycero_3_phosphocholine.py
c3p/programs/2_enoyl_CoA.py
c3p/programs/2_hydroxy_fatty_acid.py
c3p/programs/2_hydroxydicarboxylic_acid.py
c3p/programs/2_monoglyceride.py
c3p/programs/2_oxo_monocarboxylic_acid.py
c3p/programs/2_oxo_monocarboxylic_acid_anion.py
c3p/programs/3__hydroxyflavanones.py
c3p/programs/3_hydroxy_fatty_acid.py
c3p/programs/3_hydroxy_fatty_acyl_CoA.py
c3p/programs/3_hydroxy_fatty_acyl_CoA_4__.py
c3p/programs/3_oxo_5alpha_steroid.py
c3p/programs/3_oxo_5beta_steroid.py
c3p/programs/3_oxo_Delta_1__steroid.py
c3p/programs/3_oxo_Delta_4__steroid.py
c3p/programs/3_oxo_fatty_acyl_CoA.py
c3p/programs/3_oxo_fatty_acyl_CoA_4__.py
c3p/programs/3_oxo_steroid.py
c3p/programs/3_sn_phosphatidyl_L_serine.py
c3p/programs/3_substituted_propionyl_CoA_4__.py
c3p/programs/3alpha_hydroxy_steroid.py
c3p-0.5.0.dist-info/METADATA
c3p-0.5.0.dist-info/WHEEL
c3p-0.5.0.dist-info/entry_points.txt
c3p-0.5.0.dist-info/RECORD
