Metadata-Version: 2.3
Name: c3p
Version: 0.5.0
Summary: CHEBI Classification Programs
Author: Chris Mungall
Author-email: cjm@berkeleybop.org
Requires-Python: >=3.9,<4.0
Classifier: Programming Language :: Python :: 3
Classifier: Programming Language :: Python :: 3.9
Classifier: Programming Language :: Python :: 3.10
Classifier: Programming Language :: Python :: 3.11
Classifier: Programming Language :: Python :: 3.12
Classifier: Programming Language :: Python :: 3.13
Provides-Extra: eval
Provides-Extra: learn
Provides-Extra: oaklib
Requires-Dist: diskcache (>=5.6.3,<6.0.0)
Requires-Dist: jupyter ; extra == "eval"
Requires-Dist: llm ; extra == "learn"
Requires-Dist: matplotlib ; extra == "eval"
Requires-Dist: oaklib ; extra == "oaklib"
Requires-Dist: papermill ; extra == "eval"
Requires-Dist: plotly ; extra == "eval"
Requires-Dist: pydantic (>=2.10.3)
Requires-Dist: pydantic-ai (>=0.0.23,<0.0.24)
Requires-Dist: pyyaml (>=6.0.2)
Requires-Dist: rdkit (>=2024.3.5,<2025.0.0)
Requires-Dist: scikit-learn ; extra == "eval"
Requires-Dist: seaborn ; extra == "eval"
Requires-Dist: timeout-decorator (>=0.5.0,<0.6.0)
Requires-Dist: typer (>=0.14.0,<0.15.0)
